foamyguy_gradienthelper.py
foamyguy_circuitpython_gradienthelper-1.0.0.dist-info/LICENSE
foamyguy_circuitpython_gradienthelper-1.0.0.dist-info/METADATA
foamyguy_circuitpython_gradienthelper-1.0.0.dist-info/WHEEL
foamyguy_circuitpython_gradienthelper-1.0.0.dist-info/top_level.txt
foamyguy_circuitpython_gradienthelper-1.0.0.dist-info/RECORD
