Metadata-Version: 2.1
Name: foamyguy-circuitpython-gradienthelper
Version: 1.0.0
Summary: Tools for generating color gradient palettes and sha
Author-email: Adafruit Industries <circuitpython@adafruit.com>
License: MIT
Project-URL: Homepage, https://github.com/Foamyguy/Foamyguy_CircuitPython_GradientHelper
Keywords: adafruit,blinka,circuitpython,micropython,gradienthelper,color,colors,gradient,palette,displayio,shape,display
Classifier: Intended Audience :: Developers
Classifier: Topic :: Software Development :: Libraries
Classifier: Topic :: Software Development :: Embedded Systems
Classifier: Topic :: System :: Hardware
Classifier: License :: OSI Approved :: MIT License
Classifier: Programming Language :: Python :: 3
License-File: LICENSE
Requires-Dist: Adafruit-Blinka
Provides-Extra: optional
